cpfile/__init__.py
cpfile/__main__.py
FileCP-0.0.1.dist-info/METADATA
FileCP-0.0.1.dist-info/WHEEL
FileCP-0.0.1.dist-info/entry_points.txt
FileCP-0.0.1.dist-info/top_level.txt
FileCP-0.0.1.dist-info/RECORD
