Metadata-Version: 2.1
Name: FileCP
Version: 0.0.1
Summary: A CLI Tool to quickly copy file content to clipboard
Home-page: https://github.com/newtoallofthis123/cpfile
Author: NoobScience
Author-email: noobscience123@gmail.com
License: MIT
Project-URL: Author WebSite, https://newtoallofthis123.github.io/About
Project-URL: Bug Tracker, https://github.com/newtoallofthis123/cpfile/issues
Classifier: License :: OSI Approved :: MIT License
Classifier: Programming Language :: Python :: 3
Classifier: Programming Language :: Python :: 3.7
Requires-Python: >=3.6
Requires-Dist: pyperclip
